exosphere/__init__.py
exosphere/cli.py
exosphere/commands/__init__.py
exosphere/commands/config.py
exosphere/commands/host.py
exosphere/commands/inventory.py
exosphere/commands/report.py
exosphere/commands/sudo.py
exosphere/commands/ui.py
exosphere/commands/utils.py
exosphere/commands/version.py
exosphere/config.py
exosphere/context.py
exosphere/data.py
exosphere/database.py
exosphere/errors.py
exosphere/fspaths.py
exosphere/inventory.py
exosphere/main.py
exosphere/objects.py
exosphere/providers/__init__.py
exosphere/providers/api.py
exosphere/providers/debian.py
exosphere/providers/factory.py
exosphere/providers/freebsd.py
exosphere/providers/openbsd.py
exosphere/providers/redhat.py
exosphere/repl.py
exosphere/reporting.py
exosphere/schema/__init__.py
exosphere/schema/host-report.schema.json
exosphere/security.py
exosphere/setup/__init__.py
exosphere/setup/detect.py
exosphere/templates/report.html.j2
exosphere/templates/report.md.j2
exosphere/templates/report.txt.j2
exosphere/ui/__init__.py
exosphere/ui/app.py
exosphere/ui/context.py
exosphere/ui/dashboard.py
exosphere/ui/elements.py
exosphere/ui/inventory.py
exosphere/ui/logs.py
exosphere/ui/messages.py
exosphere/ui/style.tcss
exosphere_cli-2.1.2.dist-info/licenses/LICENSE
exosphere_cli-2.1.2.dist-info/WHEEL
exosphere_cli-2.1.2.dist-info/entry_points.txt
exosphere_cli-2.1.2.dist-info/METADATA
exosphere_cli-2.1.2.dist-info/RECORD
