Metadata-Version: 2.4
Name: exosphere-cli
Version: 2.1.2
Summary: CLI/TUI driven patch reporting for remote Unix-like systems.
Author: Alexandre Gauthier
Author-email: Alexandre Gauthier <alex@underwares.org>
License-Expression: MIT
License-File: LICENSE
Classifier: Development Status :: 5 - Production/Stable
Classifier: Environment :: Console
Classifier: Intended Audience :: System Administrators
Classifier: License :: OSI Approved :: MIT License
Classifier: Natural Language :: English
Classifier: Operating System :: OS Independent
Classifier: Programming Language :: Python :: 3.13
Classifier: Programming Language :: Python :: 3.14
Classifier: Topic :: System :: Monitoring
Classifier: Topic :: System :: Systems Administration
Classifier: Topic :: Utilities
Classifier: Typing :: Typed
Requires-Dist: fabric>=3.2.2
Requires-Dist: typer>=0.20.0
Requires-Dist: textual>=6.2.0
Requires-Dist: pyyaml>=6.0.3
Requires-Dist: platformdirs>=4.3.8
Requires-Dist: prompt-toolkit>=3.0.51
Requires-Dist: jinja2>=3.1.6
Requires-Dist: packaging>=24.0
Requires-Dist: rich>=14.1.0
Requires-Dist: textual-serve>=1.1.3 ; extra == 'web'
Requires-Python: >=3.13
Project-URL: homepage, https://exosphere.readthedocs.io
Project-URL: issues, https://github.com/mrdaemon/exosphere/issues
Project-URL: repository, https://github.com/mrdaemon/exosphere
Provides-Extra: web
